[
    {
        "key": "dbln",
        "value": "%7B%2261582129636635%22%3A%22hz5rs9nG%22%7D",
        "domain": "facebook.com",
        "path": "/login/device-based/",
        "hostOnly": false,
        "creation": "2025-12-12T09:13:18.000Z",
        "lastAccessed": "2025-12-12T09:13:18.012Z"
    },
    {
        "key": "datr",
        "value": "PLU7afWTds2IdwMh-_vSk37n",
        "domain": "facebook.com",
        "path": "/",
        "hostOnly": false,
        "creation": "2025-12-12T09:13:18.012Z",
        "lastAccessed": "2025-12-12T09:13:18.012Z"
    },
    {
        "key": "sb",
        "value": "PLU7aSkJ5nguVtVPC-dPi6-L",
        "domain": "facebook.com",
        "path": "/",
        "hostOnly": false,
        "creation": "2025-12-12T09:13:18.012Z",
        "lastAccessed": "2025-12-12T09:13:18.013Z"
    },
    {
        "key": "c_user",
        "value": "61582129636635",
        "domain": "facebook.com",
        "path": "/",
        "hostOnly": false,
        "creation": "2025-12-12T09:13:18.013Z",
        "lastAccessed": "2025-12-12T09:13:18.013Z"
    },
    {
        "key": "xs",
        "value": "4%3ABFbbHY1vt7vCcA%3A2%3A1765520820%3A-1%3A-1",
        "domain": "facebook.com",
        "path": "/",
        "hostOnly": false,
        "creation": "2025-12-12T09:13:18.013Z",
        "lastAccessed": "2025-12-12T09:13:18.013Z"
    },
    {
        "key": "locale",
        "value": "en_US",
        "domain": "facebook.com",
        "path": "/",
        "hostOnly": false,
        "creation": "2025-12-12T09:13:18.013Z",
        "lastAccessed": "2025-12-12T09:13:18.013Z"
    },
    {
        "key": "pas",
        "value": "61582129636635%3AmyYYmgYi94",
        "domain": "facebook.com",
        "path": "/",
        "hostOnly": false,
        "creation": "2025-12-12T09:13:18.013Z",
        "lastAccessed": "2025-12-12T09:13:18.013Z"
    },
    {
        "key": "vpd",
        "value": "v1%3B672x360x2",
        "domain": "facebook.com",
        "path": "/",
        "hostOnly": false,
        "creation": "2025-12-12T09:13:18.013Z",
        "lastAccessed": "2025-12-12T09:13:18.013Z"
    },
    {
        "key": "fr",
        "value": "0EtiJx6MogVjtUL4q.AWcze_ZvdE-szHqRTv3kroV23i-iI6wstBOnpQb1KvDylY9OtjY.BpO7U8..AAA.0.0.BpO7il.AWe0eshXzm5-D8u88Uj4Venp_ls",
        "domain": "facebook.com",
        "path": "/",
        "hostOnly": false,
        "creation": "2025-12-12T09:13:18.013Z",
        "lastAccessed": "2025-12-12T09:13:18.013Z"
    },
    {
        "key": "wl_cbv",
        "value": "v2%3Bclient_version%3A3015%3Btimestamp%3A1765521573",
        "domain": "facebook.com",
        "path": "/",
        "hostOnly": false,
        "creation": "2025-12-12T09:13:18.013Z",
        "lastAccessed": "2025-12-12T09:13:18.013Z"
    },
    {
        "key": "fbl_st",
        "value": "101222403%3BT%3A29425359",
        "domain": "facebook.com",
        "path": "/",
        "hostOnly": false,
        "creation": "2025-12-12T09:13:18.013Z",
        "lastAccessed": "2025-12-12T09:13:18.013Z"
    },
    {
        "key": "ps_l",
        "value": "1",
        "domain": "facebook.com",
        "path": "/",
        "hostOnly": false,
        "creation": "2025-12-12T09:13:18.013Z",
        "lastAccessed": "2025-12-12T09:13:18.013Z"
    },
    {
        "key": "ps_n",
        "value": "1",
        "domain": "facebook.com",
        "path": "/",
        "hostOnly": false,
        "creation": "2025-12-12T09:13:18.013Z",
        "lastAccessed": "2025-12-12T09:13:18.013Z"
    }
]
